[{"id":36,"bldg_id":11,"floor":"1","description":"Admin Floor","name":"Hotel","floor_name":"Hotel - 1"},{"id":26,"bldg_id":11,"floor":"26","description":"26th Floor","name":"Hotel","floor_name":"Hotel - 26"},{"id":27,"bldg_id":11,"floor":"27","description":"27th Floor","name":"Hotel","floor_name":"Hotel - 27"},{"id":28,"bldg_id":11,"floor":"28","description":"28th Floor","name":"Hotel","floor_name":"Hotel - 28"},{"id":29,"bldg_id":11,"floor":"29","description":"29th Floor","name":"Hotel","floor_name":"Hotel - 29"},{"id":30,"bldg_id":11,"floor":"30","description":"30th Floor","name":"Hotel","floor_name":"Hotel - 30"},{"id":31,"bldg_id":11,"floor":"31","description":"31st Floor","name":"Hotel","floor_name":"Hotel - 31"},{"id":32,"bldg_id":11,"floor":"32","description":"32nd Floor","name":"Hotel","floor_name":"Hotel - 32"},{"id":33,"bldg_id":11,"floor":"33","description":"33rd Floor","name":"Hotel","floor_name":"Hotel - 33"},{"id":34,"bldg_id":11,"floor":"34","description":"34th Floor","name":"Hotel","floor_name":"Hotel - 34"},{"id":35,"bldg_id":11,"floor":"35","description":"35th Floor","name":"Hotel","floor_name":"Hotel - 35"}]